setup.py
distributions/Binomialdistribution.py
distributions/Gaussiandistribution.py
distributions/Generaldistribution.py
distributions/__init__.py
gaus_binomial.egg-info/PKG-INFO
gaus_binomial.egg-info/SOURCES.txt
gaus_binomial.egg-info/dependency_links.txt
gaus_binomial.egg-info/not-zip-safe
gaus_binomial.egg-info/top_level.txt