Metadata-Version: 2.1
Name: gaus-binomial
Version: 7.1
Summary: Gaussian and binomial distributions
Home-page: UNKNOWN
Author: Bayangmbe Mounmo
Author-email: bayangp0@gmail.com
License: UNKNOWN
Platform: UNKNOWN
